cnb.py
util.py
canvas_nbgrader-0.1.0.dist-info/licenses/LICENSE
canvas_nbgrader-0.1.0.dist-info/METADATA
canvas_nbgrader-0.1.0.dist-info/WHEEL
canvas_nbgrader-0.1.0.dist-info/top_level.txt
canvas_nbgrader-0.1.0.dist-info/RECORD
