Metadata-Version: 2.4
Name: canvas-nbgrader
Version: 0.1.0
Summary: Add your description here
Author: Olav Vahtras
Author-email: vahtras@kth.se
Requires-Python: >=3.14
License-File: LICENSE
Requires-Dist: aiohttp>=3.13.3
Requires-Dist: canvasapi>=3.4.0
Requires-Dist: nbgrader>=0.9.5
Requires-Dist: pandas>=2.3.3
Requires-Dist: requests>=2.32.5
Requires-Dist: rich>=14.2.0
Dynamic: author
Dynamic: author-email
Dynamic: license-file
